{"time_stamp":1589892327,"file_arr":[{"Debian":[{"Docker_install.md":"Debian\/Docker_install.md"}],"FreeBSD":[{"VM_install.md":"FreeBSD\/VM_install.md"}],"Linux":[{"\u0421\u0431\u043e\u0440\u043a\u0430 Linux.md":"Linux\/\u0421\u0431\u043e\u0440\u043a\u0430 Linux.md"}],"ProxMox":[{"I2p \u0438 ssh \u0442\u0443\u043d\u0435\u043b\u0438\u0440\u043e\u0432\u0430\u043d\u0438\u0435 \u0432 ProxMox.md":"ProxMox\/I2p \u0438 ssh \u0442\u0443\u043d\u0435\u043b\u0438\u0440\u043e\u0432\u0430\u043d\u0438\u0435 \u0432 ProxMox.md"}],"QubesOs":[{"VM \u0432 QubesOs.md":"QubesOs\/VM \u0432 QubesOs.md"}],"VirtualBox":[{"\u0410\u0432\u0442\u043e\u0437\u0430\u043f\u0443\u0441\u043a VM.md":"VirtualBox\/\u0410\u0432\u0442\u043e\u0437\u0430\u043f\u0443\u0441\u043a VM.md"}]},{"Linux":{"1":{"\u0421\u0431\u043e\u0440\u043a\u0430 \u044f\u0434\u0440\u0430 Linux.md":"Linux\/\u0421\u0431\u043e\u0440\u043a\u0430 \u044f\u0434\u0440\u0430 Linux.md"}},"ProxMox":{"1":{"\u0420\u0430\u0441\u043f\u043e\u043b\u043e\u0436\u0435\u043d\u0438\u0435 \u0444\u0430\u0439\u043b\u043e\u0432 \u043a\u043e\u043d\u0444\u0438\u0433\u0443\u0440\u0430\u0446\u0438\u0438 ProxMox.md":"ProxMox\/\u0420\u0430\u0441\u043f\u043e\u043b\u043e\u0436\u0435\u043d\u0438\u0435 \u0444\u0430\u0439\u043b\u043e\u0432 \u043a\u043e\u043d\u0444\u0438\u0433\u0443\u0440\u0430\u0446\u0438\u0438 ProxMox.md"}},"VirtualBox":{"1":{"\u0421\u0431\u043e\u0440\u043a\u0430 VirtualBox.md":"VirtualBox\/\u0421\u0431\u043e\u0440\u043a\u0430 VirtualBox.md"}}},{"VirtualBox":{"2":{"\u0423\u043f\u0440\u0430\u0432\u043b\u0435\u043d\u0438\u0435 VB \u0447\u0435\u0440\u0435\u0437 \u043a\u043e\u043d\u0441\u043e\u043b\u044c.md":"VirtualBox\/\u0423\u043f\u0440\u0430\u0432\u043b\u0435\u043d\u0438\u0435 VB \u0447\u0435\u0440\u0435\u0437 \u043a\u043e\u043d\u0441\u043e\u043b\u044c.md"}}}],"menu":"<nav id='sidebarMenu' class='col-md-3 col-lg-2 d-md-block bg-light sidebar collapse'><div class='sidebar-sticky pt-3'><ul class='px-3'><li><i class='far fa-folder'><\/i><span>Debian<\/span><ul><li><i class='far fa-file'><\/i><a href='https:\/\/raw.githubusercontent.com\/smile1601\/SecurellaVM\/master\/Debian\/Docker_install.md'>Docker_install<\/a><\/li><\/ul><\/li><li><i class='far fa-folder'><\/i><span>FreeBSD<\/span><ul><li><i class='far fa-file'><\/i><a href='https:\/\/raw.githubusercontent.com\/smile1601\/SecurellaVM\/master\/FreeBSD\/VM_install.md'>VM_install<\/a><\/li><\/ul><\/li><li><i class='far fa-folder'><\/i><span>Linux<\/span><ul><li><i class='far fa-file'><\/i><a href='https:\/\/raw.githubusercontent.com\/smile1601\/SecurellaVM\/master\/Linux\/\u0421\u0431\u043e\u0440\u043a\u0430 Linux.md'>\u0421\u0431\u043e\u0440\u043a\u0430 Linux<\/a><\/li><li><i class='far fa-file'><\/i><a href='https:\/\/raw.githubusercontent.com\/smile1601\/SecurellaVM\/master\/Linux\/\u0421\u0431\u043e\u0440\u043a\u0430 \u044f\u0434\u0440\u0430 Linux.md'>\u0421\u0431\u043e\u0440\u043a\u0430 \u044f\u0434\u0440\u0430 Linux<\/a><\/li><\/ul><\/li><li><i class='far fa-folder'><\/i><span>ProxMox<\/span><ul><li><i class='far fa-file'><\/i><a href='https:\/\/raw.githubusercontent.com\/smile1601\/SecurellaVM\/master\/ProxMox\/I2p \u0438 ssh \u0442\u0443\u043d\u0435\u043b\u0438\u0440\u043e\u0432\u0430\u043d\u0438\u0435 \u0432 ProxMox.md'>I2p \u0438 ssh \u0442\u0443\u043d\u0435\u043b\u0438\u0440\u043e\u0432\u0430\u043d\u0438\u0435 \u0432 ProxMox<\/a><\/li><li><i class='far fa-file'><\/i><a href='https:\/\/raw.githubusercontent.com\/smile1601\/SecurellaVM\/master\/ProxMox\/\u0420\u0430\u0441\u043f\u043e\u043b\u043e\u0436\u0435\u043d\u0438\u0435 \u0444\u0430\u0439\u043b\u043e\u0432 \u043a\u043e\u043d\u0444\u0438\u0433\u0443\u0440\u0430\u0446\u0438\u0438 ProxMox.md'>\u0420\u0430\u0441\u043f\u043e\u043b\u043e\u0436\u0435\u043d\u0438\u0435 \u0444\u0430\u0439\u043b\u043e\u0432 \u043a\u043e\u043d\u0444\u0438\u0433\u0443\u0440\u0430\u0446\u0438\u0438 ProxMox<\/a><\/li><\/ul><\/li><li><i class='far fa-folder'><\/i><span>QubesOs<\/span><ul><li><i class='far fa-file'><\/i><a href='https:\/\/raw.githubusercontent.com\/smile1601\/SecurellaVM\/master\/QubesOs\/VM \u0432 QubesOs.md'>VM \u0432 QubesOs<\/a><\/li><\/ul><\/li><li><i class='far fa-folder'><\/i><span>VirtualBox<\/span><ul><li><i class='far fa-file'><\/i><a href='https:\/\/raw.githubusercontent.com\/smile1601\/SecurellaVM\/master\/VirtualBox\/\u0410\u0432\u0442\u043e\u0437\u0430\u043f\u0443\u0441\u043a VM.md'>\u0410\u0432\u0442\u043e\u0437\u0430\u043f\u0443\u0441\u043a VM<\/a><\/li><li><i class='far fa-file'><\/i><a href='https:\/\/raw.githubusercontent.com\/smile1601\/SecurellaVM\/master\/VirtualBox\/\u0421\u0431\u043e\u0440\u043a\u0430 VirtualBox.md'>\u0421\u0431\u043e\u0440\u043a\u0430 VirtualBox<\/a><\/li><li><i class='far fa-file'><\/i><a href='https:\/\/raw.githubusercontent.com\/smile1601\/SecurellaVM\/master\/VirtualBox\/\u0423\u043f\u0440\u0430\u0432\u043b\u0435\u043d\u0438\u0435 VB \u0447\u0435\u0440\u0435\u0437 \u043a\u043e\u043d\u0441\u043e\u043b\u044c.md'>\u0423\u043f\u0440\u0430\u0432\u043b\u0435\u043d\u0438\u0435 VB \u0447\u0435\u0440\u0435\u0437 \u043a\u043e\u043d\u0441\u043e\u043b\u044c<\/a><\/li><\/ul><\/li><\/ul><\/li><\/ul><\/div><\/nav>"}